secular_equilibrium/__init__.py
secular_equilibrium/calculator.py
secular_equilibrium/cli.py
secular_equilibrium-1.0.1.dist-info/licenses/LICENSE
secular_equilibrium-1.0.1.dist-info/METADATA
secular_equilibrium-1.0.1.dist-info/WHEEL
secular_equilibrium-1.0.1.dist-info/entry_points.txt
secular_equilibrium-1.0.1.dist-info/top_level.txt
secular_equilibrium-1.0.1.dist-info/RECORD
