Metadata-Version: 2.4
Name: secular-equilibrium
Version: 1.0.1
Summary: Secular equilibrium calculator for radioactive decay chains
Home-page: https://github.com/Josiah1/secular-eq
Author: Jinjing Li
License: MIT
Classifier: Programming Language :: Python :: 3
Classifier: License :: OSI Approved :: MIT License
Classifier: Operating System :: OS Independent
Classifier: Topic :: Scientific/Engineering :: Physics
Requires-Python: >=3.7
License-File: LICENSE
Requires-Dist: radioactivedecay>=0.6.0
Dynamic: home-page
Dynamic: license-file
Dynamic: requires-python
